[
  {
    "username": "PsyKoMari",
    "tutorials": [],
    "assignments": [],
    "score": 0
  },
  {
    "username": "RiccardoGrigoletto",
    "tutorials": [],
    "assignments": [],
    "score": 0
  },
  {
    "username": "ayoubraji",
    "tutorials": [],
    "assignments": [],
    "score": 0
  },
  {
    "username": "Ahmed-Zakii",
    "tutorials": [],
    "assignments": [],
    "score": 0
  },
  {
    "username": "Lucamoro",
    "tutorials": [],
    "assignments": [],
    "score": 0
  },
  {
    "username": "Giorgiofossati",
    "tutorials": [],
    "assignments": [],
    "score": 0
  }
]
